jspython/__init__.py
jspython-1.0.1.dist-info/LICENSE
jspython-1.0.1.dist-info/METADATA
jspython-1.0.1.dist-info/WHEEL
jspython-1.0.1.dist-info/top_level.txt
jspython-1.0.1.dist-info/RECORD
