Metadata-Version: 2.1
Name: jspython
Version: 1.0.1
Summary: Python, but JavaScript
Home-page: https://github.com/netriza/jspython
Author: Vectr0
Author-email: ayzan@netriza.ml
License: UNKNOWN
Platform: UNKNOWN
Classifier: Programming Language :: Python :: 3
Classifier: License :: OSI Approved :: MIT License
Classifier: Operating System :: OS Independent
Requires-Python: >=3.6
